uimadcad/__init__.py
uimadcad/__main__.py
uimadcad/app.py
uimadcad/ast.py
uimadcad/errorview.py
uimadcad/icon.py
uimadcad/icons/application-menu.svg
uimadcad/icons/delete-comment.svg
uimadcad/icons/dialog-warning.svg
uimadcad/icons/document-new.svg
uimadcad/icons/document-open.svg
uimadcad/icons/document-save-as.svg
uimadcad/icons/document-save.svg
uimadcad/icons/edit-comment.svg
uimadcad/icons/edit-copy.svg
uimadcad/icons/edit-find-replace.svg
uimadcad/icons/edit-find.svg
uimadcad/icons/edit-paste.svg
uimadcad/icons/edit-redo.svg
uimadcad/icons/edit-select-all.svg
uimadcad/icons/edit-undo.svg
uimadcad/icons/format-font-size-less.svg
uimadcad/icons/format-font-size-more.svg
uimadcad/icons/format-indent-less.svg
uimadcad/icons/format-indent-more.svg
uimadcad/icons/format-justify-center.svg
uimadcad/icons/go-bottom.svg
uimadcad/icons/go-down.svg
uimadcad/icons/go-jump.svg
uimadcad/icons/go-next.svg
uimadcad/icons/go-previous.svg
uimadcad/icons/go-up.svg
uimadcad/icons/insert-image.svg
uimadcad/icons/insert-text.svg
uimadcad/icons/list-add.svg
uimadcad/icons/list-remove.svg
uimadcad/icons/madcad-annotation.svg
uimadcad/icons/madcad-arc.svg
uimadcad/icons/madcad-arctangent.svg
uimadcad/icons/madcad-axis.svg
uimadcad/icons/madcad-base.svg
uimadcad/icons/madcad-boolean.svg
uimadcad/icons/madcad-boundingbox.svg
uimadcad/icons/madcad-chamfer.svg
uimadcad/icons/madcad-circle.svg
uimadcad/icons/madcad-configure-pymadcad.svg
uimadcad/icons/madcad-configure-uimadcad.svg
uimadcad/icons/madcad-cst-angle.svg
uimadcad/icons/madcad-cst-annular.svg
uimadcad/icons/madcad-cst-ball.svg
uimadcad/icons/madcad-cst-distance.svg
uimadcad/icons/madcad-cst-gear.svg
uimadcad/icons/madcad-cst-gliding.svg
uimadcad/icons/madcad-cst-helicoid.svg
uimadcad/icons/madcad-cst-onplane.svg
uimadcad/icons/madcad-cst-pivot.svg
uimadcad/icons/madcad-cst-plane.svg
uimadcad/icons/madcad-cst-projection.svg
uimadcad/icons/madcad-cst-punctiform.svg
uimadcad/icons/madcad-cst-radius.svg
uimadcad-0.8.1.dist-info/LICENSE
uimadcad-0.8.1.dist-info/METADATA
uimadcad-0.8.1.dist-info/WHEEL
uimadcad-0.8.1.dist-info/RECORD
