Metadata-Version: 2.3
Name: uimadcad
Version: 0.8.1
Summary: user-friendly graphical environment for madcad
Home-page: https://github.com/jimy-byerley/uimadcad
License: GNU GENERAL PUBLIC LICENSE
Author: jimy byerley
Author-email: jimy.byerley@gmail.com
Requires-Python: >= 3.8
Classifier: License :: OSI Approved :: GNU General Public License v3 or later (GPLv3+)
Classifier: Topic :: Scientific/Engineering
Classifier: Programming Language :: Python :: 3.8
Classifier: Programming Language :: Python :: 3.9
Classifier: Programming Language :: Python :: 3.10
Classifier: Programming Language :: Python :: 3.11
Classifier: Programming Language :: Python :: 3.12
Classifier: Programming Language :: Python :: Implementation :: CPython
Classifier: Intended Audience :: Science/Research
Classifier: Intended Audience :: Manufacturing
Classifier: Intended Audience :: Education
Classifier: Topic :: Scientific/Engineering
Classifier: Topic :: Scientific/Engineering :: Visualization
Classifier: Environment :: X11 Applications :: Qt
Requires-Dist: pnprint (>=1.3,<2.0)
Requires-Dist: processional (>=1.0,<2.0)
Requires-Dist: pymadcad[ply,stl] (>=0.19,<1.0)
Requires-Dist: pyqt5 (>=5.11,<6.0)
Requires-Dist: pyyaml (>=6,<6.1)
Project-URL: Home, https://madcad.netlify.com
Project-URL: Repository, https://github.com/jimy-byerley/uimadcad
